notionapimanager/__init__.py
notionapimanager/notion_database_api_manager.py
notionapimanager/notion_property_encoder.py
notionapimanager-0.1.10.dist-info/WHEEL
notionapimanager-0.1.10.dist-info/METADATA
notionapimanager-0.1.10.dist-info/RECORD
